setup.py
pyramid_rest/__init__.py
pyramid_rest/app.py
pyramid_rest/auth.py
pyramid_rest/config.py
pyramid_rest/decorators.py
pyramid_rest/events.py
pyramid_rest/exceptions.py
pyramid_rest/format_checker.py
pyramid_rest/helpers.py
pyramid_rest/logger.py
pyramid_rest/mapper.py
pyramid_rest/models_crud.py
pyramid_rest/querying.py
pyramid_rest/request.py
pyramid_rest/resources.py
pyramid_rest/response.py
pyramid_rest/server.py
pyramid_rest/tests.py
pyramid_rest/uml.py
pyramid_rest/view.py
pyramid_rest/admin/__init__.py
pyramid_rest/admin/api.py
pyramid_rest/admin/views.py
pyramid_rest/files/__init__.py
pyramid_rest/files/models.py
pyramid_rest/files/views.py
pyramid_rest/request_watcher/__init__.py
pyramid_rest/request_watcher/manager.py
pyramid_rest/request_watcher/models.py
pyramid_rest/request_watcher/views.py
pyramid_rest/security/__init__.py
pyramid_rest/security/decorators.py
pyramid_rest/security/functions.py
pyramid_rest/security/models.py
pyramid_rest_framework.egg-info/PKG-INFO
pyramid_rest_framework.egg-info/SOURCES.txt
pyramid_rest_framework.egg-info/dependency_links.txt
pyramid_rest_framework.egg-info/requires.txt
pyramid_rest_framework.egg-info/top_level.txt