Metadata-Version: 1.0
Name: pyramid-rest-framework
Version: 0.0.6
Summary: Rest wrapper for pyramid web server
Home-page: https://bitbucket.org/sallyruthstruik/pyramid-rest-framework
Author: Stas Kaledin
Author-email: staskaledin@gmail.com
License: UNKNOWN
Platform: UNKNOWN
